langchain_oracledb/__init__.py
langchain_oracledb/document_loaders/__init__.py
langchain_oracledb/document_loaders/oracleadb_loader.py
langchain_oracledb/document_loaders/oracleai.py
langchain_oracledb/embeddings/__init__.py
langchain_oracledb/embeddings/oracleai.py
langchain_oracledb/utilities/__init__.py
langchain_oracledb/utilities/oracleai.py
langchain_oracledb/vectorstores/__init__.py
langchain_oracledb/vectorstores/oraclevs.py
langchain_oracledb-1.0.2.dist-info/LICENSE.txt
langchain_oracledb-1.0.2.dist-info/METADATA
langchain_oracledb-1.0.2.dist-info/WHEEL
langchain_oracledb-1.0.2.dist-info/RECORD
