Metadata-Version: 2.1
Name: langchain-oracledb
Version: 1.0.2
Summary: An integration package connecting Oracle Database and LangChain
Home-page: https://github.com/oracle/langchain-oracle
License: UPL
Requires-Python: >=3.9,<4.0
Classifier: License :: Other/Proprietary License
Classifier: Programming Language :: Python :: 3
Classifier: Programming Language :: Python :: 3.9
Classifier: Programming Language :: Python :: 3.10
Classifier: Programming Language :: Python :: 3.11
Classifier: Programming Language :: Python :: 3.12
Requires-Dist: langchain-community (>=0.3.0)
Requires-Dist: langchain-core (>=0.3.15,<0.4)
Requires-Dist: numpy (>=1.21,<3)
Requires-Dist: oracledb (>=2.2.0)
Requires-Dist: pydantic (>=2,<3)
Project-URL: Repository, https://github.com/oracle/langchain-oracle
Project-URL: Source Code, https://github.com/oracle/langchain-oracle/tree/main/libs/oracledb
